myocr/__init__.py
myocr/project.py
myocr/vision.py
myocr-0.1.4.dist-info/LICENSE
myocr-0.1.4.dist-info/METADATA
myocr-0.1.4.dist-info/WHEEL
myocr-0.1.4.dist-info/top_level.txt
myocr-0.1.4.dist-info/RECORD
