Metadata-Version: 2.1
Name: myocr
Version: 0.1.4
Summary: A sample myocr package
Home-page: https://github.com/yourusername/myocr
Author: Your Name
Author-email: you@example.com
License-File: LICENSE
Requires-Dist: jupyterlab==4.2.5
Requires-Dist: opencv-python==4.10.0.84
Requires-Dist: matplotlib==3.9.2
Requires-Dist: pandas==2.2.3
Requires-Dist: tqdm==4.66.5
